icecube_simprod_histogram-0.2.1.dist-info/licenses/LICENSE
simprod_histogram/__init__.py
simprod_histogram/calc_depth_to_dataset_dirs.py
simprod_histogram/display_histos.py
simprod_histogram/py.typed
simprod_histogram/sample_dataset.py
icecube_simprod_histogram-0.2.1.dist-info/METADATA
icecube_simprod_histogram-0.2.1.dist-info/WHEEL
icecube_simprod_histogram-0.2.1.dist-info/top_level.txt
icecube_simprod_histogram-0.2.1.dist-info/RECORD
