Metadata-Version: 2.4
Name: icecube-simprod-histogram
Version: 0.2.1
Summary: Utilities for working with histograms created for simprod
Author-email: IceCube <developers@icecube.wisc.edu>
License: MIT License
Project-URL: Homepage, https://pypi.org/project/icecube-simprod-histogram/
Project-URL: Tracker, https://github.com/icecube/simprod-histogram/issues
Project-URL: Source, https://github.com/icecube/simprod-histogram
Keywords: histogram sampling,simulation,statistics
Classifier: Development Status :: 4 - Beta
Classifier: Programming Language :: Python :: 3.11
Requires-Python: <3.12,>=3.11
License-File: LICENSE
Requires-Dist: h5py
Provides-Extra: tests
Requires-Dist: h5py; extra == "tests"
Requires-Dist: pytest; extra == "tests"
Requires-Dist: matplotlib; extra == "tests"
Provides-Extra: mypy
Requires-Dist: h5py; extra == "mypy"
Requires-Dist: pytest; extra == "mypy"
Requires-Dist: matplotlib; extra == "mypy"
Provides-Extra: display
Requires-Dist: h5py; extra == "display"
Requires-Dist: matplotlib; extra == "display"
Dynamic: license-file
